rust_nurbs-0.28.0.dist-info/METADATA
rust_nurbs-0.28.0.dist-info/WHEEL
rust_nurbs-0.28.0.dist-info/licenses/LICENSE
rust_nurbs.libs/libgcc_s-5b5488a6.so.1
rust_nurbs/__init__.py
rust_nurbs/__init__.pyi
rust_nurbs/py.typed
rust_nurbs/rust_nurbs.pypy39-pp73-arm-linux-gnu.so
rust_nurbs-0.28.0.dist-info/RECORD
